{
  "name": "Tidelight High Noon",
  "type": "light",
  "colors": {
    "focusBorder": "#0e7490",

    "foreground": "#020617",
    "descriptionForeground": "#1e293b",
    "errorForeground": "#9f1239",

    "editor.background": "#ffffff",
    "editor.foreground": "#020617",

    "editorLineNumber.foreground": "#64748b",
    "editorLineNumber.activeForeground": "#1e293b",

    "editorCursor.foreground": "#0e7490",
    "editor.selectionBackground": "#0e74902b",
    "editor.inactiveSelectionBackground": "#0e749020",
    "editor.wordHighlightBackground": "#0284c722",
    "editor.wordHighlightStrongBackground": "#0284c73a",
    "editor.findMatchBackground": "#f59e0b55",
    "editor.findMatchHighlightBackground": "#f59e0b33",
    "editor.hoverHighlightBackground": "#0e749018",
    "editor.lineHighlightBackground": "#02061708",

    "editorIndentGuide.background1": "#cbd5e1",
    "editorIndentGuide.activeBackground1": "#64748b",

    "editorBracketMatch.background": "#0e74901f",
    "editorBracketMatch.border": "#0e749066",

    "editorGroupHeader.tabsBackground": "#e5e7eb",
    "tab.activeBackground": "#ffffff",
    "tab.inactiveBackground": "#e5e7eb",
    "tab.activeForeground": "#020617",
    "tab.inactiveForeground": "#1e293b",
    "tab.border": "#cbd5e1",

    "activityBar.background": "#e5e7eb",
    "activityBar.foreground": "#020617",
    "activityBar.inactiveForeground": "#475569",
    "activityBar.border": "#cbd5e1",

    "sideBar.background": "#e5e7eb",
    "sideBar.foreground": "#020617",
    "sideBar.border": "#cbd5e1",
    "sideBarTitle.foreground": "#020617",

    "list.activeSelectionBackground": "#0e74902b",
    "list.activeSelectionForeground": "#020617",
    "list.hoverBackground": "#0206170a",
    "list.hoverForeground": "#020617",
    "list.inactiveSelectionBackground": "#02061708",

    "statusBar.background": "#e5e7eb",
    "statusBar.foreground": "#020617",
    "statusBar.border": "#cbd5e1",
    "statusBar.debuggingBackground": "#1d4ed8",
    "statusBar.debuggingForeground": "#ffffff",

    "titleBar.activeBackground": "#e5e7eb",
    "titleBar.activeForeground": "#020617",
    "titleBar.inactiveBackground": "#e5e7eb",
    "titleBar.inactiveForeground": "#475569",

    "panel.background": "#ffffff",
    "panel.border": "#cbd5e1",

    "terminal.background": "#ffffff",
    "terminal.foreground": "#020617",
    "terminalCursor.foreground": "#0e7490",
    "terminal.ansiBlack": "#020617",
    "terminal.ansiBlue": "#1d4ed8",
    "terminal.ansiCyan": "#0e7490",
    "terminal.ansiGreen": "#15803d",
    "terminal.ansiMagenta": "#a21caf",
    "terminal.ansiRed": "#9f1239",
    "terminal.ansiYellow": "#a16207",
    "terminal.ansiWhite": "#1e293b",

    "input.background": "#f8fafc",
    "input.foreground": "#020617",
    "input.placeholderForeground": "#475569",
    "input.border": "#cbd5e1",

    "dropdown.background": "#f8fafc",
    "dropdown.foreground": "#020617",
    "dropdown.border": "#cbd5e1",

    "badge.background": "#0e7490",
    "badge.foreground": "#ffffff",

    "notificationCenterHeader.background": "#e5e7eb",
    "notifications.background": "#f8fafc",
    "notifications.foreground": "#020617",
    "notifications.border": "#cbd5e1",

    "editorOverviewRuler.errorForeground": "#9f1239cc",
    "editorOverviewRuler.warningForeground": "#a16207cc",
    "editorOverviewRuler.infoForeground": "#1d4ed8cc",

    "gitDecoration.addedResourceForeground": "#15803d",
    "gitDecoration.modifiedResourceForeground": "#1d4ed8",
    "gitDecoration.deletedResourceForeground": "#9f1239",
    "gitDecoration.untrackedResourceForeground": "#0e7490",
    "gitDecoration.ignoredResourceForeground": "#64748b"
  },
  "tokenColors": [
    {
      "name": "Comments",
      "scope": ["comment", "punctuation.definition.comment"],
      "settings": { "foreground": "#475569", "fontStyle": "italic" }
    },

    {
      "name": "Strings",
      "scope": ["string", "punctuation.definition.string"],
      "settings": { "foreground": "#166534" }
    },
    {
      "name": "Template strings / interpolation",
      "scope": [
        "string.template",
        "punctuation.definition.template-expression",
        "punctuation.section.embedded",
        "meta.template.expression"
      ],
      "settings": { "foreground": "#0e7490" }
    },

    {
      "name": "Numbers",
      "scope": ["constant.numeric"],
      "settings": { "foreground": "#a16207" }
    },
    {
      "name": "Language constants (true/false/null/etc.)",
      "scope": ["constant.language"],
      "settings": { "foreground": "#a21caf" }
    },

    {
      "name": "Keywords",
      "scope": [
        "keyword",
        "storage.type",
        "storage.modifier",
        "keyword.control",
        "keyword.operator.new",
        "keyword.operator.expression",
        "keyword.operator.logical"
      ],
      "settings": { "foreground": "#0e7490" }
    },

    {
      "name": "Operators / punctuation",
      "scope": ["keyword.operator", "punctuation", "meta.brace", "meta.delimiter"],
      "settings": { "foreground": "#1e293b" }
    },

    {
      "name": "Functions",
      "scope": [
        "entity.name.function",
        "support.function",
        "meta.function-call",
        "meta.method-call"
      ],
      "settings": { "foreground": "#1d4ed8" }
    },

    {
      "name": "Parameters",
      "scope": ["variable.parameter", "meta.parameters", "meta.function.parameters"],
      "settings": { "foreground": "#020617" }
    },

    {
      "name": "Variables",
      "scope": ["variable", "meta.definition.variable", "entity.name.variable"],
      "settings": { "foreground": "#020617" }
    },

    {
      "name": "Constants",
      "scope": ["variable.other.constant", "entity.name.constant"],
      "settings": { "foreground": "#a16207" }
    },

    {
      "name": "Types",
      "scope": [
        "entity.name.type",
        "support.type",
        "support.class",
        "entity.name.class",
        "entity.name.interface",
        "entity.name.struct",
        "entity.name.enum"
      ],
      "settings": { "foreground": "#312e81" }
    },

    {
      "name": "Type parameters / generics",
      "scope": ["entity.name.type.parameter", "meta.type.parameters", "meta.type.annotation"],
      "settings": { "foreground": "#0e7490" }
    },

    {
      "name": "Language keywords for modules (import/export/etc.)",
      "scope": ["keyword.control.import", "keyword.control.export", "keyword.control.from", "keyword.control.as"],
      "settings": { "foreground": "#0e7490" }
    },

    {
      "name": "Self references (this/self/super)",
      "scope": ["variable.language.this", "variable.language.super", "variable.language.self"],
      "settings": { "foreground": "#a21caf" }
    },

    {
      "name": "Property names",
      "scope": ["variable.other.property", "support.variable.property"],
      "settings": { "foreground": "#4338ca" }
    },

    {
      "name": "Tags (HTML/XML/JSX)",
      "scope": ["entity.name.tag"],
      "settings": { "foreground": "#0e7490" }
    },
    {
      "name": "Attributes (HTML/XML/JSX)",
      "scope": ["entity.other.attribute-name"],
      "settings": { "foreground": "#312e81" }
    },

    {
      "name": "Invalid / deprecated",
      "scope": ["invalid", "invalid.deprecated"],
      "settings": { "foreground": "#9f1239", "fontStyle": "underline" }
    },

    {
      "name": "JSON keys (Tidelight High Noon)",
      "scope": [
        "support.type.property-name.json",
        "meta.object-literal.key.json string.quoted.double.json",
        "meta.object.member.json string.quoted.double.json"
      ],
      "settings": { "foreground": "#4338ca" }
    },
    {
      "name": "JSON string values (Tidelight High Noon)",
      "scope": [
        "meta.object-literal.value.json string.quoted.double.json",
        "meta.array.literal.json string.quoted.double.json",
        "string.quoted.double.json"
      ],
      "settings": { "foreground": "#166534" }
    },
    {
      "name": "JSON numbers (Tidelight High Noon)",
      "scope": ["constant.numeric.json"],
      "settings": { "foreground": "#a16207" }
    },
    {
      "name": "JSON booleans & null (Tidelight High Noon)",
      "scope": [
        "constant.language.boolean.json",
        "constant.language.null.json",
        "constant.language.json"
      ],
      "settings": { "foreground": "#a21caf" }
    },
    {
      "name": "JSON punctuation (Tidelight High Noon)",
      "scope": [
        "punctuation.support.type.property-name.json",
        "punctuation.separator.dictionary.key-value.json",
        "punctuation.definition.dictionary.begin.json",
        "punctuation.definition.dictionary.end.json",
        "punctuation.definition.array.begin.json",
        "punctuation.definition.array.end.json",
        "punctuation.separator.array.json"
      ],
      "settings": { "foreground": "#1e293b" }
    },

    {
      "name": "Markdown headings",
      "scope": [
        "markup.heading",
        "entity.name.section.markdown",
        "markup.heading.markdown punctuation.definition.heading.markdown"
      ],
      "settings": { "foreground": "#0e7490", "fontStyle": "bold" }
    },
    {
      "name": "Markdown bold",
      "scope": ["markup.bold", "punctuation.definition.bold"],
      "settings": { "foreground": "#020617", "fontStyle": "bold" }
    },
    {
      "name": "Markdown italic",
      "scope": ["markup.italic", "punctuation.definition.italic"],
      "settings": { "foreground": "#020617", "fontStyle": "italic" }
    },
    {
      "name": "Markdown inline code",
      "scope": ["markup.inline.raw", "markup.inline.raw.string.markdown"],
      "settings": { "foreground": "#166534" }
    },
    {
      "name": "Markdown code blocks",
      "scope": ["markup.fenced_code.block", "markup.raw.block"],
      "settings": { "foreground": "#020617" }
    },
    {
      "name": "Markdown links",
      "scope": ["markup.underline.link", "meta.link.inline", "meta.link.reference"],
      "settings": { "foreground": "#1d4ed8", "fontStyle": "underline" }
    },

    {
      "name": "Diff inserted",
      "scope": ["markup.inserted", "diff.inserted", "meta.diff.header.to-file"],
      "settings": { "foreground": "#166534" }
    },
    {
      "name": "Diff deleted",
      "scope": ["markup.deleted", "diff.deleted", "meta.diff.header.from-file"],
      "settings": { "foreground": "#9f1239" }
    },
    {
      "name": "Diff changed",
      "scope": ["markup.changed", "diff.changed"],
      "settings": { "foreground": "#a16207" }
    },

    {
      "name": "TODO / FIXME / NOTE",
      "scope": [
        "comment.keyword.todo",
        "comment.keyword.fixme",
        "comment.keyword.note",
        "keyword.other.todo",
        "keyword.other.fixme",
        "keyword.other.note"
      ],
      "settings": { "foreground": "#a16207", "fontStyle": "bold" }
    },

    {
      "name": "Regex (common scopes)",
      "scope": [
        "string.regexp",
        "string.regexp keyword.other",
        "string.regexp punctuation.definition.string",
        "string.regexp punctuation.definition.group",
        "string.regexp punctuation.definition.character-class",
        "string.regexp constant.character.escape"
      ],
      "settings": { "foreground": "#0e7490" }
    }
  ],
  "semanticHighlighting": true,
  "semanticTokenColors": {
    "namespace": "#312e81",
    "class": "#312e81",
    "interface": "#312e81",
    "type": "#312e81",
    "typeParameter": "#0e7490",
    "parameter": "#020617",
    "property": "#4338ca",
    "variable": "#020617",
    "function": "#1d4ed8",
    "method": "#1d4ed8",
    "keyword": "#0e7490",
    "string": "#166534",
    "number": "#a16207"
  }
}